logdir/__init__.py
logdir-0.13.0.dist-info/LICENSE
logdir-0.13.0.dist-info/METADATA
logdir-0.13.0.dist-info/WHEEL
logdir-0.13.0.dist-info/RECORD
