Metadata-Version: 2.1
Name: logdir
Version: 0.13.0
Summary: A utility for managing logging directories.
Home-page: https://logdir.btjanaka.net
License: MIT
Keywords: log,logging,utilities
Author: Bryon Tjanaka
Author-email: bryon@btjanaka.net
Requires-Python: >=3.7,<4.0
Classifier: Development Status :: 4 - Beta
Classifier: License :: OSI Approved :: MIT License
Classifier: Programming Language :: Python :: 3
Classifier: Programming Language :: Python :: 3.7
Classifier: Programming Language :: Python :: 3.8
Classifier: Programming Language :: Python :: 3.9
Classifier: Programming Language :: Python :: 3.10
Classifier: Programming Language :: Python :: 3.11
Classifier: Topic :: System :: Logging
Classifier: Topic :: Utilities
Requires-Dist: dulwich (>=0.20.0)
Requires-Dist: python-slugify (>=4.0.0)
Requires-Dist: ruamel.yaml (>0.15)
Requires-Dist: shortuuid (>=1.0.11)
Requires-Dist: toml (>=0.10)
Project-URL: Documentation, https://logdir.btjanaka.net
Project-URL: Repository, https://github.com/btjanaka/logdir
